MANIFEST.in
README.md
setup.py
voyeur.py
aws_voyeur.egg-info/PKG-INFO
aws_voyeur.egg-info/SOURCES.txt
aws_voyeur.egg-info/dependency_links.txt
aws_voyeur.egg-info/entry_points.txt
aws_voyeur.egg-info/requires.txt
aws_voyeur.egg-info/top_level.txt