Metadata-Version: 1.1
Name: aws-voyeur
Version: 0.1.2
Summary: List AWS inventory
Home-page: https://github.com/texastribune/aws-voyeur
Author: Chris Chang
Author-email: cchang@texastribune.org
License: BSD
Platform: UNKNOWN
Classifier: Development Status :: 4 - Beta
Classifier: Intended Audience :: Developers
Classifier: License :: OSI Approved :: BSD License
Classifier: Operating System :: OS Independent
Classifier: Programming Language :: Python
